utf8cleaner/__init__.py
utf8cleaner/cleaner.py
utf8cleaner/cli.py
utf8cleaner-0.0.2.dist-info/METADATA
utf8cleaner-0.0.2.dist-info/WHEEL
utf8cleaner-0.0.2.dist-info/entry_points.txt
utf8cleaner-0.0.2.dist-info/top_level.txt
utf8cleaner-0.0.2.dist-info/RECORD
