Metadata-Version: 2.1
Name: utf8cleaner
Version: 0.0.2
Summary: remove non-UTF8 bytes from an input file and write a cleaned up version
Home-page: https://github.com/GeoffWilliams/utf8cleaner.git
Author: Geoff Williams
Author-email: geoff@declarativesystems.com
License: UNKNOWN
Platform: UNKNOWN
Classifier: Development Status :: 1 - Planning
Classifier: Programming Language :: Python :: 3
Classifier: License :: OSI Approved :: Apache Software License
Classifier: Operating System :: OS Independent
Requires-Python: >=3.6
